{
 "info": {
  "video_path": "earth9-4.mp4",
  "url": "",
  "class": "documentary film",
  "w": 1280,
  "h": 720,
  "num_frame": 10500,
  "fps": 25
 },
 "caption": "This video segment introduces a unique ecological environment in the Arabian Sea, a life chain composed of fishing ants and other organisms. They play important roles in this ocean, providing a significant amount of oxygen and food to the ecosystem. Their presence also attracts predators such as sharks, creating a complex ecosystem.Fishing ants play crucial roles in the Arabian Sea. They support the ecosystem by expelling oxygen and other consumable substances. They are preyed upon by a range of warm-water creatures, including sharks. Individual fishing ants are tiny, but collectively, they produce one-third of the oxygen in our atmosphere. - Warm seawater in the Arabian Sea plays a vital role. It sustains a large population of fish. Predators like sharks also inhabit this ocean. - Complexity of the ecological environment: Fishing ants and other organisms form a life chain. They depend on each other, constituting a complex ecosystem. This ocean is a vibrant environment with rich biodiversity. - Arabian Sea fishing ants are the most abundant animals on Earth. A single ant can hold up to two million tons. - Importance of ecosystems: Every species within an ecosystem has its role and interdependence. Their presence and existence are significant for the entire ecosystem. - Warm seawater in the Arabian Sea is essential for supporting the ecosystem. It provides an ample supply of oxygen and food for the ecosystem. - Balance in the ecosystem: Each species has its way of survival, competing and relying on each other. This balance is a crucial factor in maintaining ecosystem stability.",
 "global": [
  {
   "question": "Are there more then three different backgrounds appearing in the video?",
   "answer": "Yes."
  },
  {
   "question": "Are there any human?",
   "answer": "No."
  },
  {
   "question": "Does it happen in the cities?",
   "answer": "No."
  },
  {
   "question": "Does it happen indoor or outdoor?",
   "answer": "Outdoor."
  },
  {
   "question": "Does it happen during day or night?",
   "answer": "Day."
  }
 ],
 "breakpoint": [
  {
   "time": 25,
   "question": "What is the scene?",
   "answer": "Birds."
  },
  {
   "time": 750,
   "question": "Are there any animals?",
   "answer": "Yes."
  },
  {
   "time": 1500,
   "question": "What is the background color?",
   "answer": "Yellow."
  },
  {
   "time": 2250,
   "question": "What is the background color?",
   "answer": "Yellow."
  },
  {
   "time": 3000,
   "question": "Where is it?",
   "answer": "Underwater."
  },
  {
   "time": 3750,
   "question": "What is the scene?",
   "answer": "Two whales."
  },
  {
   "time": 4500,
   "question": "What is the scene?",
   "answer": "The earth."
  },
  {
   "time": 5250,
   "question": "Where is it?",
   "answer": "In the ocean."
  },
  {
   "time": 6000,
   "question": "Are there any water?",
   "answer": "Yes."
  },
  {
   "time": 6750,
   "question": "Are there any water?",
   "answer": "Yes."
  },
  {
   "time": 7500,
   "question": "What is the scene?",
   "answer": "The earth."
  },
  {
   "time": 8250,
   "question": "Are there any animals?",
   "answer": "Yes."
  },
  {
   "time": 9000,
   "question": "Are there any human?",
   "answer": "No."
  },
  {
   "time": 9750,
   "question": "What kind of animal is it?",
   "answer": "Pawn."
  },
  {
   "time": 10500,
   "question": "What kind of animal is it?",
   "answer": "Fish."
  }
 ]
}