{
    "info":
    {
        "video_path": "SHQ-9.mp4",
        "url": "",
        "class": "Adventure Film",
        "w": 1280,
        "h": 720,
        "num_frame": 11250,
        "fps": 25.00
    },
    "caption": "However, the ball he snatched from Charlie's hand was fake, and the real ball was hidden in his friend's clothes. The boss was very angry and ordered everyone to get the ball back. At this moment, Jack, who was on a mission outside, learned that his house had been invaded. He immediately terminated the mission and returned, intending to rescue the children. In the secret headquarters, the children and the team were in a fierce battle. Although the child used the weapons in the room, they still couldn’t beat the team because they had too many members. At the last moment, they threw the ball into the portal and then destroyed the portal.",
    "global":
    [
        {
            "question":"Is it a video based on reality or not?(Does it looks like real story? Or it looks like a science fiction movie?)",
            "answer":"No. It seems like a science fiction movie"
        },
        {
            "question":"Are there more then five different places appear in the video(scene switch doesn't necessarily means a place change)?",
            "answer":"No."
        },
        {
            "question":"Is there more than three different characters appear?",
            "answer":"Yes."
        },
        {
            "question":"what time does the video take place?(at day time or night time?)",
            "answer":"Mainly at night time."
        },
        {
            "question":"Where does the video take place? Indoors or outdoors?",
            "answer":"Mainly indoors."
        }
    ],
    "breakpoint":
    [
        {
            "time":750, 
            "question":"Is it indoors or outdoors?",
            "answer":"It's indoors."
        },
        {
            "time":1500,
            "question":"what's in the scene?",
            "answer":"A shining ball is rolling."
        },
        {
            "time":2150,
            "question":"Is it at daytime or at night time?",
            "answer":"It's at night time."
        },
        {
            "time":3000, 
            "question":"Is it indoors or outdoors?",
            "answer":"It's indoors."
        },
        {
            "time":3750,
            "question":"what's the girl doing?",
            "answer":"She's throwing a shining ball to her friend."
        },
        {
            "time":4450,
            "question":"what is the boy's hair color?",
            "answer":"Golden."
        },
        {
            "time":5350,
            "question":"How many characters appear in the scene?",
            "answer":"Two."
        },
        {
            "time":6000,
            "question":"Is it at daytime or at night time?",
            "answer":"It's at night time."
        },
        {
            "time":6850, 
            "question":"Is it indoors or outdoors?",
            "answer":"It's indoors."
        },
        {
            "time":7500,
            "question":"Is it indoors or outdoors?",
            "answer":"It's indoors."
        },
        {
            "time":8250,
            "question":"Is there any character appears?",
            "answer":"Yes."
        },
        {
            "time":9000, 
            "question":"Is the man bald?",
            "answer":"No."
        },
        {
            "time":9750,
            "question":"where is the scene?",
            "answer":"Over a big city."
        },
        {
            "time":10600, 
            "question":"Is there more than five people?",
            "answer":"No."
        },
        {
            "time":10875,
            "question":"Is there more than three people?",
            "answer":"No."
        }
    ]
}